{
  "generated_at": "2026-07-06T23:36:25.300068Z",
  "target_date": "2026-07-06",
  "vix": {
    "value": 15.57,
    "prev": 16.15,
    "chg_abs": -0.58,
    "chg_pct": -3.5913,
    "date": "2026-07-06"
  },
  "move": {
    "value": 65.7632,
    "prev": 65.4,
    "chg_abs": 0.363197,
    "chg_pct": 0.5553,
    "date": "2026-07-06"
  },
  "y2": {
    "value": 4.13,
    "prev": 4.14,
    "chg_abs": -0.01,
    "chg_pct": -0.2415,
    "date": "2026-07-06"
  },
  "y10": {
    "value": 4.48,
    "prev": 4.49,
    "chg_abs": -0.01,
    "chg_pct": -0.2227,
    "date": "2026-07-06"
  },
  "y30": {
    "value": 4.99,
    "prev": 4.98,
    "chg_abs": 0.01,
    "chg_pct": 0.2008,
    "date": "2026-07-06"
  },
  "spread": 35.0,
  "sox": {
    "value": 12900.1416,
    "prev": 12626.2197,
    "chg_abs": 273.921875,
    "chg_pct": 2.1695,
    "date": "2026-07-06"
  },
  "stocks": {
    "NVDA": {
      "value": 195.55,
      "prev": 194.83,
      "chg_abs": 0.720001,
      "chg_pct": 0.3696,
      "date": "2026-07-06",
      "name": "輝達",
      "emoji": "🟢",
      "grade": "IG1"
    },
    "TSM": {
      "value": 451.79,
      "prev": 434.16,
      "chg_abs": 17.630005,
      "chg_pct": 4.0607,
      "date": "2026-07-06",
      "name": "台積電",
      "emoji": "🔵",
      "grade": "IG1"
    },
    "SMCI": {
      "value": 27.19,
      "prev": 27.22,
      "chg_abs": -0.029999,
      "chg_pct": -0.1102,
      "date": "2026-07-06",
      "name": "超微電腦",
      "emoji": "⚡",
      "grade": "HY1"
    },
    "ARM": {
      "value": 322.24,
      "prev": 315.28,
      "chg_abs": 6.959991,
      "chg_pct": 2.2076,
      "date": "2026-07-06",
      "name": "安謀控股",
      "emoji": "💻",
      "grade": "IG1"
    },
    "TSLA": {
      "value": 419.77,
      "prev": 393.45,
      "chg_abs": 26.319977,
      "chg_pct": 6.6895,
      "date": "2026-07-06",
      "name": "特斯拉",
      "emoji": "🚗",
      "grade": "IG3"
    }
  }
}