{
  "generated_at": "2026-04-07T23:05:32.301883Z",
  "target_date": "2026-04-07",
  "vix": {
    "value": 25.78,
    "prev": 24.17,
    "chg_abs": 1.610001,
    "chg_pct": 6.6612,
    "date": "2026-04-07"
  },
  "move": {
    "value": 83.1452,
    "prev": 81.68,
    "chg_abs": 1.465202,
    "chg_pct": 1.7938,
    "date": "2026-04-07"
  },
  "y2": {
    "value": 3.81,
    "prev": 3.84,
    "chg_abs": -0.03,
    "chg_pct": -0.7812,
    "date": "2026-04-07"
  },
  "y10": {
    "value": 4.33,
    "prev": 4.34,
    "chg_abs": -0.01,
    "chg_pct": -0.2304,
    "date": "2026-04-07"
  },
  "y30": {
    "value": 4.9,
    "prev": 4.89,
    "chg_abs": 0.01,
    "chg_pct": 0.2045,
    "date": "2026-04-07"
  },
  "spread": 52.0,
  "sox": {
    "value": 8003.8677,
    "prev": 7916.1099,
    "chg_abs": 87.757812,
    "chg_pct": 1.1086,
    "date": "2026-04-07"
  },
  "stocks": {
    "NVDA": {
      "value": 178.1,
      "prev": 177.64,
      "chg_abs": 0.460007,
      "chg_pct": 0.259,
      "date": "2026-04-07",
      "name": "輝達",
      "emoji": "🟢",
      "grade": "IG1"
    },
    "TSM": {
      "value": 345.32,
      "prev": 341.76,
      "chg_abs": 3.559998,
      "chg_pct": 1.0417,
      "date": "2026-04-07",
      "name": "台積電",
      "emoji": "🔵",
      "grade": "IG1"
    },
    "SMCI": {
      "value": 22.67,
      "prev": 22.05,
      "chg_abs": 0.620001,
      "chg_pct": 2.8118,
      "date": "2026-04-07",
      "name": "超微電腦",
      "emoji": "⚡",
      "grade": "HY1"
    },
    "ARM": {
      "value": 143.86,
      "prev": 148.77,
      "chg_abs": -4.910004,
      "chg_pct": -3.3004,
      "date": "2026-04-07",
      "name": "安謀控股",
      "emoji": "💻",
      "grade": "IG1"
    },
    "TSLA": {
      "value": 346.65,
      "prev": 352.82,
      "chg_abs": -6.170013,
      "chg_pct": -1.7488,
      "date": "2026-04-07",
      "name": "特斯拉",
      "emoji": "🚗",
      "grade": "IG3"
    }
  }
}